README.rst
setup.cfg
setup.py
somber/__init__.py
somber/base.py
somber/lissom.py
somber/ng.py
somber/sequential.py
somber/som.py
somber.egg-info/PKG-INFO
somber.egg-info/SOURCES.txt
somber.egg-info/dependency_links.txt
somber.egg-info/requires.txt
somber.egg-info/top_level.txt
somber.egg-info/zip-safe
somber/components/__init__.py
somber/components/initializers.py
somber/components/utilities.py