Metadata-Version: 1.1
Name: somber
Version: 2.0.1
Summary: Self-Organizing Maps in Numpy
Home-page: https://github.com/stephantul/somber
Author: Stéphan Tulkens
Author-email: stephan.tulkens@uantwerpen.be
License: MIT
Keywords: self-organizing maps machine learning unsupervised
Platform: UNKNOWN
Classifier: Intended Audience :: Developers
Classifier: Programming Language :: Python :: 3
